odoo/addons/account_analytic_distribution_widget_rebalance/README.rst
odoo/addons/account_analytic_distribution_widget_rebalance/__init__.py
odoo/addons/account_analytic_distribution_widget_rebalance/__manifest__.py
odoo/addons/account_analytic_distribution_widget_rebalance/i18n/account_analytic_distribution_widget_rebalance.pot
odoo/addons/account_analytic_distribution_widget_rebalance/i18n/it.po
odoo/addons/account_analytic_distribution_widget_rebalance/readme/CONTRIBUTORS.md
odoo/addons/account_analytic_distribution_widget_rebalance/readme/DESCRIPTION.md
odoo/addons/account_analytic_distribution_widget_rebalance/readme/USAGE.md
odoo/addons/account_analytic_distribution_widget_rebalance/static/description/icon.png
odoo/addons/account_analytic_distribution_widget_rebalance/static/description/index.html
odoo/addons/account_analytic_distribution_widget_rebalance/static/img/step1.png
odoo/addons/account_analytic_distribution_widget_rebalance/static/img/step2.png
odoo/addons/account_analytic_distribution_widget_rebalance/static/img/step3.png
odoo/addons/account_analytic_distribution_widget_rebalance/static/src/AnalyticDistribution.esm.js
odoo/addons/account_analytic_distribution_widget_rebalance/static/src/AnalyticDistribution.scss
odoo/addons/account_analytic_distribution_widget_rebalance/static/src/AnalyticDistribution.xml
odoo/addons/account_analytic_distribution_widget_rebalance/static/tests/AnalyticDistribution.esm.js
odoo/addons/account_analytic_distribution_widget_rebalance/tests/__init__.py
odoo/addons/account_analytic_distribution_widget_rebalance/tests/test_qunit.py
odoo_addon_account_analytic_distribution_widget_rebalance-17.0.1.0.0.4.dist-info/METADATA
odoo_addon_account_analytic_distribution_widget_rebalance-17.0.1.0.0.4.dist-info/WHEEL
odoo_addon_account_analytic_distribution_widget_rebalance-17.0.1.0.0.4.dist-info/top_level.txt
odoo_addon_account_analytic_distribution_widget_rebalance-17.0.1.0.0.4.dist-info/RECORD
